CHANGES.txt
MANIFEST.in
README.txt
setup.py
src/django_counters/__init__.py
src/django_counters/base.py
src/django_counters/munin_plugin.py
src/django_counters/view_counters.py
src/django_counters.egg-info/PKG-INFO
src/django_counters.egg-info/SOURCES.txt
src/django_counters.egg-info/dependency_links.txt
src/django_counters.egg-info/not-zip-safe
src/django_counters.egg-info/requires.txt
src/django_counters.egg-info/top_level.txt