Metadata-Version: 1.0
Name: django-counters
Version: 0.2
Summary: A Django app adding PyCounters to Django and offering admin like interface for the monitored info.
Home-page: UNKNOWN
Author: DjangoCounters Developers
Author-email: b.leskes@gmail.com
License: apache
Platform: UNKNOWN
